Metadata-Version: 2.1
Name: kwaddle
Version: 0.5
Summary: UNKNOWN
Home-page: https://github.com/andrewtmmaher/waddle
Author: Andrew Maher
Author-email: andrewtmmaher@gmail.com
License: UNKNOWN
Platform: UNKNOWN
Classifier: Programming Language :: Python :: 3
Classifier: License :: OSI Approved :: MIT License
Classifier: Operating System :: OS Independent
